svg_tools/__init__.py
svg_tools/__main__.py
svg_tools/util.py
blue_dot_sessions_svg_tools-0.5.0.dist-info/LICENSE
blue_dot_sessions_svg_tools-0.5.0.dist-info/WHEEL
blue_dot_sessions_svg_tools-0.5.0.dist-info/METADATA
blue_dot_sessions_svg_tools-0.5.0.dist-info/RECORD
