Metadata-Version: 2.1
Name: blue-dot-sessions-svg-tools
Version: 0.5.0
Summary: SVG tools for Blue Dot Sessions
License: MIT
Author: Dean Shaff
Author-email: dean.shaff@gmail.com
Requires-Python: >=3.6,<4.0
Classifier: License :: OSI Approved :: MIT License
Classifier: Programming Language :: Python :: 3
Classifier: Programming Language :: Python :: 3.6
Classifier: Programming Language :: Python :: 3.7
Classifier: Programming Language :: Python :: 3.8
Requires-Dist: numpy (>=1.18.4,<2.0.0)
